{
  "project_info": {
    "project_number": "77025911882",
    "project_id": "daily-shepherd-633f3",
    "storage_bucket": "daily-shepherd-633f3.firebasestorage.app"
  },
  "client": [
    {
      "client_info": {
        "mobilesdk_app_id": "1:77025911882:android:e3c5508561dfba6da972b3",
        "android_client_info": {
          "package_name": "com.daily_shepherd"
        }
      },
      "oauth_client": [
        {
          "client_id": "77025911882-38knj3gobjf8490723d3p0jirbrabqvn.apps.googleusercontent.com",
          "client_type": 3
        }
      ],
      "api_key": [
        {
          "current_key": "AIzaSyAlbZSb8e7jzlXTMFR43PMiLzC8l_hScFg"
        }
      ],
      "services": {
        "appinvite_service": {
          "other_platform_oauth_client": [
            {
              "client_id": "77025911882-38knj3gobjf8490723d3p0jirbrabqvn.apps.googleusercontent.com",
              "client_type": 3
            }
          ]
        }
      }
    }
  ],
  "configuration_version": "1"
}